uk_boards/__init__.py
uk_boards/charities.py
uk_boards/cli.py
uk_boards/companies.py
uk_boards/uk_boards.py
uk_boards/utils.py
uk_boards-0.4.0.dist-info/AUTHORS.rst
uk_boards-0.4.0.dist-info/LICENSE
uk_boards-0.4.0.dist-info/METADATA
uk_boards-0.4.0.dist-info/WHEEL
uk_boards-0.4.0.dist-info/entry_points.txt
uk_boards-0.4.0.dist-info/top_level.txt
uk_boards-0.4.0.dist-info/RECORD
