Metadata-Version: 2.1
Name: uk-boards
Version: 0.4.0
Summary: Query UK company and charity board networks.
Home-page: https://github.com/spool/uk_boards
Author: Griffith Rees
Author-email: griff.rees@gmail.com
License: MIT
Keywords: uk_boards
Platform: UNKNOWN
Classifier: Development Status :: 2 - Pre-Alpha
Classifier: Intended Audience :: Developers
Classifier: License :: OSI Approved :: MIT License
Classifier: Natural Language :: English
Classifier: Programming Language :: Python :: 3 :: Only
Classifier: Programming Language :: Python :: 3.6
Classifier: Programming Language :: Python :: 3.7
Classifier: Programming Language :: Python :: 3.8
Classifier: Topic :: Scientific/Engineering :: Information Analysis
Requires-Python: !=3.0.*, !=3.1.*, !=3.2.*, !=3.3.*, !=3.4.*, !=3.5*
Requires-Dist: Click (>=7.0)
Requires-Dist: networkx (>=2.4)
Requires-Dist: requests (>=2.22.0)
Requires-Dist: zeep (>=3.4.0)
Requires-Dist: python-dotenv (>=0.10.3)
